SQL_Tracker/SQL_tracker.py
SQL_Tracker/__init__.py
SQL_Tracker-0.1.0.dist-info/License
SQL_Tracker-0.1.0.dist-info/METADATA
SQL_Tracker-0.1.0.dist-info/WHEEL
SQL_Tracker-0.1.0.dist-info/top_level.txt
SQL_Tracker-0.1.0.dist-info/RECORD
