Metadata-Version: 2.1
Name: SQL_Tracker
Version: 0.1.0
Summary: Real-time SQL query tracking and lineage visualization.
Home-page: https://github.com/sagarsambhwani/SQL_Tracker
Author: Sagar Sambhwani
Author-email: sagar.2001.a20@gmail.com
Classifier: Programming Language :: Python :: 3
Classifier: License :: OSI Approved :: MIT License
Classifier: Operating System :: OS Independent
Requires-Python: >=3.6
License-File: License
Requires-Dist: sqlparse >=0.4.4
Requires-Dist: prettytable >=3.6.0
